nightskycam_images/__init__.py
nightskycam_images/annotator_webapp.py
nightskycam_images/constants.py
nightskycam_images/convert_npy.py
nightskycam_images/filters.py
nightskycam_images/folder_change.py
nightskycam_images/image.py
nightskycam_images/main.py
nightskycam_images/patches.py
nightskycam_images/py.typed
nightskycam_images/stats.py
nightskycam_images/templates/annotator/index.html
nightskycam_images/templates/base.html
nightskycam_images/templates/viewer/index.html
nightskycam_images/templates/viewer/list.html
nightskycam_images/thumbnail.py
nightskycam_images/version.py
nightskycam_images/video.py
nightskycam_images/view_webapp.py
nightskycam_images/walk.py
nightskycam_images/weather.py
nightskycam_images-0.1.5.dist-info/METADATA
nightskycam_images-0.1.5.dist-info/WHEEL
nightskycam_images-0.1.5.dist-info/entry_points.txt
nightskycam_images-0.1.5.dist-info/RECORD
