Metadata-Version: 2.4
Name: nightskycam-images
Version: 0.1.5
Summary: 
Author: Vincent Berenz
Author-email: vincent.berenz@tuebingen.mpg.de
Requires-Python: >=3.12,<3.14
Classifier: Programming Language :: Python :: 3
Classifier: Programming Language :: Python :: 3.12
Classifier: Programming Language :: Python :: 3.13
Requires-Dist: astropy (>=7.2.0,<8.0.0)
Requires-Dist: auto-stretch (>=0.0.3,<0.0.4)
Requires-Dist: flask (>=3.1.2,<4.0.0)
Requires-Dist: imageio (>=2.37.2,<3.0.0)
Requires-Dist: loguru (>=0.7.3,<0.8.0)
Requires-Dist: nightskycam-scorer (>=0.2.1,<0.3.0)
Requires-Dist: opencv-python (>=4.12.0.88,<5.0.0.0)
Requires-Dist: pillow (>=12.0.0,<13.0.0)
Requires-Dist: rich (>=14.2.0,<15.0.0)
Requires-Dist: scikit-learn (>=1.7.2,<2.0.0)
Requires-Dist: tifffile (>=2025.10.16,<2026.0.0)
Requires-Dist: toml (>=0.10.2,<0.11.0)
Requires-Dist: tomli (>=2.3.0,<3.0.0)
Requires-Dist: tomli-w (>=1.2.0,<2.0.0)
Requires-Dist: torch (>=2.9.1,<3.0.0)
Requires-Dist: torchvision (>=0.24.1,<0.25.0)
Requires-Dist: typer (>=0.20.0,<0.21.0)
